[
    {
        "timestamp": "2026-07-15T11:32:31.216919+05:30",
        "message_id": "false_120363407511560539@g.us_ACC667BAEAB097C875D2D28FEC889352_183189079388242@lid",
        "sender": "[Production & Mortality Mohan updates] Venkatamohan (919121923600)",
        "sender_name": "Venkatamohan",
        "is_group": true,
        "group_name": "Production & Mortality Mohan updates",
        "raw_text": "Shead 3\nProlapsed",
        "ai_extracted": {
            "shead_name": "",
            "category": "unknown",
            "quantity": 0,
            "unit": "",
            "amount": 0.0,
            "notes": "AI processing failed or unreachable",
            "confidence_score": 0.0,
            "processed_text": "Shead 3\nProlapsed"
        }
    },
    {
        "timestamp": "2026-07-15T11:32:34.660019+05:30",
        "message_id": "false_120363407511560539@g.us_ACAC0044BAB5F71BEDAC6E51E8472802_183189079388242@lid",
        "sender": "[Production & Mortality Mohan updates] Venkatamohan (919121923600)",
        "sender_name": "Venkatamohan",
        "is_group": true,
        "group_name": "Production & Mortality Mohan updates",
        "raw_text": "Shead 8\nFaty liver",
        "ai_extracted": {
            "shead_name": "",
            "category": "unknown",
            "quantity": 0,
            "unit": "",
            "amount": 0.0,
            "notes": "AI processing failed or unreachable",
            "confidence_score": 0.0,
            "processed_text": "Shead 8\nFaty liver"
        }
    },
    {
        "timestamp": "2026-07-15T11:35:07.027487+05:30",
        "message_id": "false_120363212822578807@g.us_AC581D9FC0CEA6595059613649E2A322_92282304913416@lid",
        "sender": "[120363212822578807] V (917893108780)",
        "sender_name": "V",
        "is_group": true,
        "group_name": "120363212822578807",
        "raw_text": "Shead3 water spraying",
        "ai_extracted": null
    },
    {
        "timestamp": "2026-07-15T11:35:10.451126+05:30",
        "message_id": "false_120363225998735559@g.us_ACB165984AF002018653A4DA8A760EDC_241274569400567@lid",
        "sender": "[Gate Manager] NABIYABHANU (918247256522)",
        "sender_name": "NABIYABHANU",
        "is_group": true,
        "group_name": "Gate Manager",
        "raw_text": "Out to chavatagunta  to bring meterials and  food",
        "ai_extracted": {
            "shead_name": "",
            "category": "unknown",
            "quantity": 0,
            "unit": "",
            "amount": 0.0,
            "notes": "AI processing failed or unreachable",
            "confidence_score": 0.0,
            "processed_text": "Out to chavatagunta  to bring meterials and  food"
        }
    },
    {
        "timestamp": "2026-07-15T11:36:52.583354+05:30",
        "message_id": "false_120363046205890693@g.us_ACF86C449E5F444B690B9C8A1F80BEED_241274569400567@lid",
        "sender": "[120363046205890693] NABIYABHANU (918247256522)",
        "sender_name": "NABIYABHANU",
        "is_group": true,
        "group_name": "120363046205890693",
        "raw_text": "",
        "ai_extracted": null
    },
    {
        "timestamp": "2026-07-15T11:37:40.568141+05:30",
        "message_id": "false_120363421181996594@g.us_3EB05214A64EFA4FFCDBA1_184791135711366@lid",
        "sender": "[Raw Material Prices & Ordering] mahalakshmi (916364817749)",
        "sender_name": "mahalakshmi",
        "is_group": true,
        "group_name": "Raw Material Prices & Ordering",
        "raw_text": "Raw material",
        "ai_extracted": {
            "shead_name": "",
            "category": "unknown",
            "quantity": 0,
            "unit": "",
            "amount": 0.0,
            "notes": "AI processing failed or unreachable",
            "confidence_score": 0.0,
            "processed_text": "Raw material"
        }
    },
    {
        "timestamp": "2026-07-15T11:37:49.419641+05:30",
        "message_id": "false_120363212822578807@g.us_AC37155E044A120DD95BCA62CFEEE309_281265026629807@lid",
        "sender": "[Farm Supervisors] Cute_ Boy_ 13 \ud83e\udd70 (916202757898)",
        "sender_name": "Cute_ Boy_ 13 \ud83e\udd70",
        "is_group": true,
        "group_name": "Farm Supervisors",
        "raw_text": "Sed 8\nSpreying",
        "ai_extracted": null
    },
    {
        "timestamp": "2026-07-15T11:37:54.769220+05:30",
        "message_id": "false_120363421181996594@g.us_3EB003C0EEDFBBA39F53C6_184791135711366@lid",
        "sender": "[120363421181996594] mahalakshmi (916364817749)",
        "sender_name": "mahalakshmi",
        "is_group": true,
        "group_name": "120363421181996594",
        "raw_text": "Feed medicine",
        "ai_extracted": {
            "shead_name": "",
            "category": "unknown",
            "quantity": 0,
            "unit": "",
            "amount": 0.0,
            "notes": "AI processing failed or unreachable",
            "confidence_score": 0.0,
            "processed_text": "Feed medicine"
        }
    },
    {
        "timestamp": "2026-07-15T11:38:03.710176+05:30",
        "message_id": "false_120363212822578807@g.us_AC3618826887819C36969814333E0E37_281265026629807@lid",
        "sender": "[Farm Supervisors] Cute_ Boy_ 13 \ud83e\udd70 (916202757898)",
        "sender_name": "Cute_ Boy_ 13 \ud83e\udd70",
        "is_group": true,
        "group_name": "Farm Supervisors",
        "raw_text": "",
        "ai_extracted": null
    },
    {
        "timestamp": "2026-07-15T11:38:05.127000+05:30",
        "message_id": "false_120363046205890693@g.us_AC7E4E7A150FC5F72340EBD9E25A491B_241274569400567@lid",
        "sender": "[Egg Gowdown & Sales] NABIYABHANU (918247256522)",
        "sender_name": "NABIYABHANU",
        "is_group": true,
        "group_name": "Egg Gowdown & Sales",
        "raw_text": "Flys \ud83e\udeb0  medicine",
        "ai_extracted": null
    },
    {
        "timestamp": "2026-07-15T11:38:15.743310+05:30",
        "message_id": "false_120363405469158412@g.us_3EB032570A8DC199BC6B17_184791135711366@lid",
        "sender": "[Payments - Sunfra Farms] mahalakshmi (916364817749)",
        "sender_name": "mahalakshmi",
        "is_group": true,
        "group_name": "Payments - Sunfra Farms",
        "raw_text": "Zoho subscription",
        "ai_extracted": {
            "shead_name": "",
            "category": "unknown",
            "quantity": 0,
            "unit": "",
            "amount": 0.0,
            "notes": "AI processing failed or unreachable",
            "confidence_score": 0.0,
            "processed_text": "Zoho subscription"
        }
    },
    {
        "timestamp": "2026-07-15T11:42:41.491873+05:30",
        "message_id": "false_120363405469158412@g.us_3EB06409935209DE43308A_184791135711366@lid",
        "sender": "[Payments - Sunfra Farms] mahalakshmi (916364817749)",
        "sender_name": "mahalakshmi",
        "is_group": true,
        "group_name": "Payments - Sunfra Farms",
        "raw_text": "zoho subscription",
        "ai_extracted": {
            "shead_name": "Shead 3",
            "category": "unknown",
            "quantity": null,
            "unit": null,
            "amount": 1060.82,
            "notes": "zoho subscription charges",
            "confidence_score": 1.0,
            "processed_text": "Transaction has been successfully completed!"
        }
    },
    {
        "timestamp": "2026-07-15T11:42:57.820256+05:30",
        "message_id": "false_120363212822578807@g.us_AC1DBB6D975941E82B3B99A1BD0DEEBE_92282304913416@lid",
        "sender": "[Farm Supervisors] V (917893108780)",
        "sender_name": "V",
        "is_group": true,
        "group_name": "Farm Supervisors",
        "raw_text": "Shead1 water spraying",
        "ai_extracted": null
    },
    {
        "timestamp": "2026-07-15T11:49:09.554060+05:30",
        "message_id": "false_120363212822578807@g.us_AC6ECDFBD11634E4C92BEAAFD234DB92_281265026629807@lid",
        "sender": "[120363212822578807] Cute_ Boy_ 13 \ud83e\udd70 (916202757898)",
        "sender_name": "Cute_ Boy_ 13 \ud83e\udd70",
        "is_group": true,
        "group_name": "120363212822578807",
        "raw_text": "Sed 6 \nSpreying",
        "ai_extracted": null
    },
    {
        "timestamp": "2026-07-15T11:49:18.414930+05:30",
        "message_id": "false_120363225998735559@g.us_ACA5FA81148A96DCB6C7E76E9C3D0B54_241274569400567@lid",
        "sender": "[Gate Manager] NABIYABHANU (918247256522)",
        "sender_name": "NABIYABHANU",
        "is_group": true,
        "group_name": "Gate Manager",
        "raw_text": "Out",
        "ai_extracted": {
            "shead_name": "Shead 1",
            "category": "unknown",
            "quantity": null,
            "unit": null,
            "amount": null,
            "notes": "Out",
            "confidence_score": 0.95,
            "processed_text": "A person is sitting on a motorcycle."
        }
    },
    {
        "timestamp": "2026-07-15T11:49:28.143505+05:30",
        "message_id": "false_120363426039486670@g.us_ACAA94EEA141A9C397B85F7DC24915A5_26049698091190@lid",
        "sender": "[Cash & Attendance] Nani Chinnam (917204041105)",
        "sender_name": "Nani Chinnam",
        "is_group": true,
        "group_name": "Cash & Attendance",
        "raw_text": "450000/- cash deposited to account",
        "ai_extracted": null
    },
    {
        "timestamp": "2026-07-15T11:51:18.778140+05:30",
        "message_id": "false_120363212822578807@g.us_AC47584A8408515C85A0EB0CD22AF9B2_231275432571022@lid",
        "sender": "[120363212822578807] tprasanth390 (918179905257)",
        "sender_name": "tprasanth390",
        "is_group": true,
        "group_name": "120363212822578807",
        "raw_text": "4th Shead water spraying",
        "ai_extracted": null
    },
    {
        "timestamp": "2026-07-15T11:51:35.317090+05:30",
        "message_id": "false_120363426039486670@g.us_ACF256D990E13FBB88ABC4A733BBDA78_26049698091190@lid",
        "sender": "[120363426039486670] Nani Chinnam (917204041105)",
        "sender_name": "Nani Chinnam",
        "is_group": true,
        "group_name": "120363426039486670",
        "raw_text": "",
        "ai_extracted": {
            "shead_name": "Sunfra Farm",
            "category": "unknown",
            "quantity": null,
            "unit": null,
            "amount": 450000,
            "notes": "",
            "confidence_score": 1.0,
            "processed_text": "State Bank of India DEPOSIT/PAY IN SLIP\nDate | 15/07/2026\nSB/C/A/RD/OD/CC/TL/DLA/c No / Credit Card No.\n42539035698\nName Sunfra Farm\nTel. No\nAmount 4,50,000.00\nRupees in words Four Lakh\nEX: Six Thousand Rupees only\nCheque No./Date/Name of Bank & Branch | 16483\nSBI toll-free. 24 Hours Call Centre\nNo. 18004253800, 1800112211\nSWO / Passing Officer"
        }
    },
    {
        "timestamp": "2026-07-15T11:52:13.774462+05:30",
        "message_id": "false_120363212822578807@g.us_AC290C126F16ABE2B65323185373C9F1_281265026629807@lid",
        "sender": "[Farm Supervisors] Cute_ Boy_ 13 \ud83e\udd70 (916202757898)",
        "sender_name": "Cute_ Boy_ 13 \ud83e\udd70",
        "is_group": true,
        "group_name": "Farm Supervisors",
        "raw_text": "Sed 6 \nFlushout",
        "ai_extracted": null
    },
    {
        "timestamp": "2026-07-15T11:54:16.836827+05:30",
        "message_id": "false_120363212822578807@g.us_AC75ABCA2A55B7B44F8E3853DB30AA0E_281265026629807@lid",
        "sender": "[Farm Supervisors] Cute_ Boy_ 13 \ud83e\udd70 (916202757898)",
        "sender_name": "Cute_ Boy_ 13 \ud83e\udd70",
        "is_group": true,
        "group_name": "Farm Supervisors",
        "raw_text": "Sed 7\nSpreying",
        "ai_extracted": null
    },
    {
        "timestamp": "2026-07-15T11:54:17.459861+05:30",
        "message_id": "false_120363212822578807@g.us_ACC8F98B78F88027864B413CC3AEDC95_281265026629807@lid",
        "sender": "[Farm Supervisors] Cute_ Boy_ 13 \ud83e\udd70 (916202757898)",
        "sender_name": "Cute_ Boy_ 13 \ud83e\udd70",
        "is_group": true,
        "group_name": "Farm Supervisors",
        "raw_text": "",
        "ai_extracted": null
    }
]